src/Prediction.py
src/__init__.py
automationobjectdetection_sandeepjena7-0.0.1.dist-info/LICENSE
automationobjectdetection_sandeepjena7-0.0.1.dist-info/METADATA
automationobjectdetection_sandeepjena7-0.0.1.dist-info/WHEEL
automationobjectdetection_sandeepjena7-0.0.1.dist-info/top_level.txt
automationobjectdetection_sandeepjena7-0.0.1.dist-info/RECORD
